<gmd:MD_Metadata xmlns:gmd="http://www.isotc211.org/2005/gmd" xmlns:gml="http://www.opengis.net/gml"
                 xmlns:gco="http://www.isotc211.org/2005/gco"
                 xmlns:xsi="http://www.w3.org/2001/XMLSchema-instance"
                 xsi:schemaLocation="http://www.isotc211.org/2005/gmd http://www.isotc211.org/2005/gmd/gmd.xsd http://www.isotc211.org/2005/gmx http://www.isotc211.org/2005/gmx/gmx.xsd http://www.isotc211.org/2005/srv http://schemas.opengis.net/iso/19139/20060504/srv/srv.xsd">
  <gmd:fileIdentifier>
      <gco:CharacterString></gco:CharacterString>
  </gmd:fileIdentifier>
  <gmd:language>
      <gmd:LanguageCode codeList="http://www.loc.gov/standards/iso639-2/" codeListValue="ger"/>
  </gmd:language>
  <gmd:characterSet>
      <gmd:MD_CharacterSetCode codeListValue="utf8"
                               codeList="http://standards.iso.org/ittf/PubliclyAvailableStandards/ISO_19139_Schemas/resources/codelist/ML_gmxCodelists.xml#MD_CharacterSetCode"/>
  </gmd:characterSet>
  <gmd:contact>
      <gmd:CI_ResponsibleParty>
         <gmd:organisationName>
            <gco:CharacterString>actinia-gdi</gco:CharacterString>
         </gmd:organisationName>
         <gmd:role>
            <gmd:CI_RoleCode codeListValue="originator"
                             codeList="http://standards.iso.org/ittf/PubliclyAvailableStandards/ISO_19139_Schemas/resources/codelist/ML_gmxCodelists.xml#CI_RoleCode"/>
         </gmd:role>
      </gmd:CI_ResponsibleParty>
  </gmd:contact>
  <gmd:dateStamp>
      <gco:DateTime>2018-07-19T06:43:42</gco:DateTime>
  </gmd:dateStamp>
  <gmd:metadataStandardName>
      <gco:CharacterString>ISO 19115:2003/19139</gco:CharacterString>
  </gmd:metadataStandardName>
  <gmd:metadataStandardVersion>
      <gco:CharacterString>1.0</gco:CharacterString>
  </gmd:metadataStandardVersion>
  <gmd:dataSetURI gco:nilReason="missing">
      <gco:CharacterString/>
  </gmd:dataSetURI>
  <gmd:referenceSystemInfo>
      <gmd:MD_ReferenceSystem>
         <gmd:referenceSystemIdentifier>
            <gmd:RS_Identifier>
               <gmd:code>
                  <gco:CharacterString>EPSG:25832</gco:CharacterString>
               </gmd:code>
            </gmd:RS_Identifier>
         </gmd:referenceSystemIdentifier>
      </gmd:MD_ReferenceSystem>
  </gmd:referenceSystemInfo>
  <gmd:identificationInfo>
      <gmd:MD_DataIdentification>
         <gmd:citation>
            <gmd:CI_Citation>
               <gmd:title>
                  <gco:CharacterString>{{ title}}</gco:CharacterString>
               </gmd:title>
               <gmd:date>
                  <gmd:CI_Date>
                     <gmd:date>
                        <gco:Date/>
                     </gmd:date>
                     <gmd:dateType>
                        <gmd:CI_DateTypeCode codeList="http://standards.iso.org/ittf/PubliclyAvailableStandards/ISO_19139_Schemas/resources/codelist/ML_gmxCodelists.xml#CI_DateTypeCode"
                                             codeListValue="publication"/>
                     </gmd:dateType>
                  </gmd:CI_Date>
               </gmd:date>
            </gmd:CI_Citation>
         </gmd:citation>
         <gmd:abstract gco:nilReason="missing">
            <gco:CharacterString/>
         </gmd:abstract>
         <gmd:purpose gco:nilReason="missing">
            <gco:CharacterString/>
         </gmd:purpose>
         <gmd:pointOfContact>
            <gmd:CI_ResponsibleParty>
               <gmd:individualName>
                  <gco:CharacterString>T. Adams</gco:CharacterString>
               </gmd:individualName>
               <gmd:organisationName>
                  <gco:CharacterString>mundialisT</gco:CharacterString>
               </gmd:organisationName>
               <gmd:contactInfo>
                  <gmd:CI_Contact>
                     <gmd:address>
                        <gmd:CI_Address>
                           <gmd:electronicMailAddress>
                              <gco:CharacterString>adams@mundialis.de</gco:CharacterString>
                           </gmd:electronicMailAddress>
                        </gmd:CI_Address>
                     </gmd:address>
                  </gmd:CI_Contact>
               </gmd:contactInfo>
               <gmd:role>
                  <gmd:CI_RoleCode codeListValue="pointOfContact"
                                   codeList="http://standards.iso.org/ittf/PubliclyAvailableStandards/ISO_19139_Schemas/resources/codelist/ML_gmxCodelists.xml#CI_RoleCode"/>
               </gmd:role>
            </gmd:CI_ResponsibleParty>
         </gmd:pointOfContact>
         <gmd:resourceMaintenance>
            <gmd:MD_MaintenanceInformation>
               <gmd:maintenanceAndUpdateFrequency>
                  <gmd:MD_MaintenanceFrequencyCode codeListValue="asNeeded"
                                                   codeList="http://standards.iso.org/ittf/PubliclyAvailableStandards/ISO_19139_Schemas/resources/codelist/ML_gmxCodelists.xml#MD_MaintenanceFrequencyCode"/>
               </gmd:maintenanceAndUpdateFrequency>
            </gmd:MD_MaintenanceInformation>
         </gmd:resourceMaintenance>
         <gmd:resourceConstraints>
            <gmd:MD_LegalConstraints>
               <gmd:accessConstraints>
                  <gmd:MD_RestrictionCode codeListValue=""
                                          codeList="http://standards.iso.org/ittf/PubliclyAvailableStandards/ISO_19139_Schemas/resources/codelist/ML_gmxCodelists.xml#MD_RestrictionCode"/>
               </gmd:accessConstraints>
               <gmd:useConstraints>
                  <gmd:MD_RestrictionCode codeListValue=""
                                          codeList="http://standards.iso.org/ittf/PubliclyAvailableStandards/ISO_19139_Schemas/resources/codelist/ML_gmxCodelists.xml#MD_RestrictionCode"/>
               </gmd:useConstraints>
               <gmd:otherConstraints gco:nilReason="missing">
                  <gco:CharacterString/>
               </gmd:otherConstraints>
            </gmd:MD_LegalConstraints>
         </gmd:resourceConstraints>
         <gmd:spatialRepresentationType>
            <gmd:MD_SpatialRepresentationTypeCode codeListValue="vector"
                                                  codeList="http://standards.iso.org/ittf/PubliclyAvailableStandards/ISO_19139_Schemas/resources/codelist/ML_gmxCodelists.xml#MD_SpatialRepresentationTypeCode"/>
         </gmd:spatialRepresentationType>
         <gmd:spatialResolution>
            <gmd:MD_Resolution>
               <gmd:equivalentScale>
                  <gmd:MD_RepresentativeFraction>
                     <gmd:denominator/>
                  </gmd:MD_RepresentativeFraction>
               </gmd:equivalentScale>
            </gmd:MD_Resolution>
         </gmd:spatialResolution>
         <gmd:language>
            <gco:CharacterString>eng</gco:CharacterString>
         </gmd:language>
         <gmd:characterSet>
            <gmd:MD_CharacterSetCode codeListValue="utf8"
                                     codeList="http://standards.iso.org/ittf/PubliclyAvailableStandards/ISO_19139_Schemas/resources/codelist/ML_gmxCodelists.xml#MD_CharacterSetCode"/>
         </gmd:characterSet>
         <gmd:extent>
            <gmd:EX_Extent>
               <gmd:temporalElement>
                  <gmd:EX_TemporalExtent>
                     <gmd:extent>
                        <gml:TimePeriod gml:id="d87969e243a1050910">
                           <gml:beginPosition>2018-01-01</gml:beginPosition>
                           <gml:endPosition>2020-12-31</gml:endPosition>
                        </gml:TimePeriod>
                     </gmd:extent>
                  </gmd:EX_TemporalExtent>
               </gmd:temporalElement>
            </gmd:EX_Extent>
         </gmd:extent>
         <gmd:extent>
            <gmd:EX_Extent>
               <gmd:geographicElement>
                  <gmd:EX_GeographicBoundingBox>
                     <gmd:westBoundLongitude>
                        <gco:Decimal>-180</gco:Decimal>
                     </gmd:westBoundLongitude>
                     <gmd:eastBoundLongitude>
                        <gco:Decimal>180</gco:Decimal>
                     </gmd:eastBoundLongitude>
                     <gmd:southBoundLatitude>
                        <gco:Decimal>-90</gco:Decimal>
                     </gmd:southBoundLatitude>
                     <gmd:northBoundLatitude>
                        <gco:Decimal>90</gco:Decimal>
                     </gmd:northBoundLatitude>
                  </gmd:EX_GeographicBoundingBox>
               </gmd:geographicElement>
            </gmd:EX_Extent>
         </gmd:extent>
      </gmd:MD_DataIdentification>
  </gmd:identificationInfo>
  <gmd:distributionInfo>
      <gmd:MD_Distribution>
         <gmd:distributionFormat>
            <gmd:MD_Format>
               <gmd:name gco:nilReason="missing">
                  <gco:CharacterString/>
               </gmd:name>
               <gmd:version gco:nilReason="missing">
                  <gco:CharacterString/>
               </gmd:version>
            </gmd:MD_Format>
         </gmd:distributionFormat>
         <gmd:transferOptions>
            <gmd:MD_DigitalTransferOptions>
               <gmd:onLine>
                  <gmd:CI_OnlineResource>
                     <gmd:linkage>
                        <gmd:URL/>
                     </gmd:linkage>
                     <gmd:protocol gco:nilReason="missing">
                        <gco:CharacterString/>
                     </gmd:protocol>
                  </gmd:CI_OnlineResource>
               </gmd:onLine>
            </gmd:MD_DigitalTransferOptions>
         </gmd:transferOptions>
      </gmd:MD_Distribution>
  </gmd:distributionInfo>
  <gmd:dataQualityInfo>
      <gmd:DQ_DataQuality>
         <gmd:scope>
            <gmd:DQ_Scope>
               <gmd:level>
                  <gmx:MX_ScopeCode xmlns:gmx="http://www.isotc211.org/2005/gmx" codeList="" codeListValue=""/>
               </gmd:level>
               <gmd:levelDescription>
                  <gmd:MD_ScopeDescription>
                     <gmd:other>
                        <gco:CharacterString>specifies the extent, spatial and/or temporal, and/or common characteristic(s) that identify the data on which data quality was to be evaluated.</gco:CharacterString>
                     </gmd:other>
                  </gmd:MD_ScopeDescription>
               </gmd:levelDescription>
            </gmd:DQ_Scope>
         </gmd:scope>
         <gmd:lineage>
            <gmd:LI_Lineage>
               <gmd:statement gco:nilReason="missing">
                  <gco:CharacterString/>
               </gmd:statement>
               <gmd:processStep>
                  <gmd:LI_ProcessStep>
                     <gmd:description gco:nilReason="missing">
                        <gco:CharacterString/>
                     </gmd:description>
                  </gmd:LI_ProcessStep>
               </gmd:processStep>
            </gmd:LI_Lineage>
         </gmd:lineage>
      </gmd:DQ_DataQuality>
  </gmd:dataQualityInfo>
</gmd:MD_Metadata>
